cfddns_updater/__init__.py
cfddns_updater/__main__.py
cfddns_updater/_version.py
cfddns_updater/config.py
cfddns_updater/fixed_cloudflare_ddns.py
cfddns_updater/main.py
cfdyndns_updater-0.1.0.dist-info/LICENSE
cfdyndns_updater-0.1.0.dist-info/METADATA
cfdyndns_updater-0.1.0.dist-info/WHEEL
cfdyndns_updater-0.1.0.dist-info/entry_points.txt
cfdyndns_updater-0.1.0.dist-info/top_level.txt
cfdyndns_updater-0.1.0.dist-info/RECORD
