Metadata-Version: 2.1
Name: cfdyndns-updater
Version: 0.1.0
Summary: A script to keep the values in the Cloudflare DDNS service in sync with your local dynamic IP address.
Home-page: https://github.com/kozalosev/cfddns-updater
Author: Leonid Kozarin
Author-email: kozalo@sadbot.ru
License: MIT
Keywords: cloudflare dns ddns domain dynamic ip address update
Platform: UNKNOWN
Classifier: Development Status :: 4 - Beta
Classifier: Environment :: Console
Classifier: Intended Audience :: System Administrators
Classifier: License :: OSI Approved :: MIT License
Classifier: Natural Language :: English
Classifier: Operating System :: OS Independent
Classifier: Programming Language :: Python
Classifier: Programming Language :: Python :: 3.6
Classifier: Programming Language :: Python :: 3 :: Only
Classifier: Topic :: Internet :: Name Service (DNS)
Requires-Dist: cloudflare-ddns
Requires-Dist: PyYAML
